{
  "version": "5",
  "dialect": "sqlite",
  "entries": [
    {
      "idx": 0,
      "version": "5",
      "when": 1713967825302,
      "tag": "0000_shocking_peter_parker",
      "breakpoints": true
    },
    {
      "idx": 1,
      "version": "5",
      "when": 1713997649126,
      "tag": "0001_lively_marvel_apes",
      "breakpoints": true
    },
    {
      "idx": 2,
      "version": "5",
      "when": 1714126307901,
      "tag": "0002_hot_goblin_queen",
      "breakpoints": true
    }
  ]
}